htcompile/__init__.py
htcompile/__main__.py
htcompile/cli.py
htcompile/parser.py
htcompile-0.0.6.dist-info/METADATA
htcompile-0.0.6.dist-info/WHEEL
htcompile-0.0.6.dist-info/entry_points.txt
htcompile-0.0.6.dist-info/licenses/LICENSE
htcompile-0.0.6.dist-info/RECORD
