Metadata-Version: 2.4
Name: htcompile
Version: 0.0.6
Summary: A static import compiler for HTML pages.
Project-URL: Homepage, https://kittkat.xyz/projects/htcompile/
Project-URL: Issues, https://github.com/KittKat7/htcompile/issues
Author-email: KittKat <kittkat@kittkat.xyz>
License-Expression: GPL-3.0-or-later
License-File: LICENSE
Classifier: Operating System :: OS Independent
Classifier: Programming Language :: Python :: 3
Requires-Python: >=3.8
